aa_rag/__init__.py
aa_rag/exceptions.py
aa_rag/main.py
aa_rag/oss.py
aa_rag/settings.py
aa_rag/utils.py
aa_rag/db/__init__.py
aa_rag/db/base.py
aa_rag/db/lancedb_.py
aa_rag/db/milvus_.py
aa_rag/db/mongo_.py
aa_rag/db/multimodal.py
aa_rag/db/tinydb_.py
aa_rag/engine/__init__.py
aa_rag/engine/base.py
aa_rag/engine/lightrag.py
aa_rag/engine/simple_chunk.py
aa_rag/gtypes/__init__.py
aa_rag/gtypes/enums.py
aa_rag/gtypes/models/__init__.py
aa_rag/gtypes/models/base.py
aa_rag/gtypes/models/delete.py
aa_rag/gtypes/models/index.py
aa_rag/gtypes/models/parse.py
aa_rag/gtypes/models/retrieve.py
aa_rag/gtypes/models/statistic.py
aa_rag/gtypes/models/knowlege_base/__init__.py
aa_rag/gtypes/models/knowlege_base/base.py
aa_rag/gtypes/models/knowlege_base/qa.py
aa_rag/gtypes/models/knowlege_base/solution.py
aa_rag/knowledge_base/__init__.py
aa_rag/knowledge_base/base.py
aa_rag/knowledge_base/built_in/__init__.py
aa_rag/knowledge_base/built_in/qa.py
aa_rag/knowledge_base/built_in/solution.py
aa_rag/parse/__init__.py
aa_rag/parse/base.py
aa_rag/parse/markitdown.py
aa_rag/router/__init__.py
aa_rag/router/delete.py
aa_rag/router/index.py
aa_rag/router/qa.py
aa_rag/router/retrieve.py
aa_rag/router/solution.py
aa_rag/router/statistic.py
aa_rag-0.4.3.dist-info/METADATA
aa_rag-0.4.3.dist-info/WHEEL
aa_rag-0.4.3.dist-info/entry_points.txt
aa_rag-0.4.3.dist-info/licenses/LICENSE
aa_rag-0.4.3.dist-info/RECORD
