Metadata-Version: 2.4
Name: aa-rag
Version: 0.4.3
Summary: RAG server for ai2apps.
Author-email: jarlor <jarlorzhang@outlook.com>
License-File: LICENSE
Requires-Python: >=3.10
Requires-Dist: boto3
Requires-Dist: fastapi[standard]==0.115.12
Requires-Dist: fastmcp>=2.2.0
Requires-Dist: jieba==0.42.1
Requires-Dist: langchain-community==0.3.21
Requires-Dist: langchain-core==0.3.51
Requires-Dist: langchain-milvus==0.1.9
Requires-Dist: langchain-openai==0.3.12
Requires-Dist: langchain==0.3.23
Requires-Dist: markitdown==0.1.1
Requires-Dist: nltk==3.9.1
Requires-Dist: openai==1.72.0
Requires-Dist: pandas==2.2.3
Requires-Dist: pydantic-settings==2.8.1
Requires-Dist: pymilvus==2.5.6
Requires-Dist: python-dotenv==1.0.1
Requires-Dist: rank-bm25==0.2.2
Requires-Dist: tinydb==4.8.2
Provides-Extra: lightrag
Requires-Dist: future>=1.0.0; extra == 'lightrag'
Requires-Dist: graspologic; extra == 'lightrag'
Requires-Dist: lightrag-hku>=1.2.2; extra == 'lightrag'
Requires-Dist: nano-vectordb>=0.0.4.3; extra == 'lightrag'
Requires-Dist: networkx>=3.4.2; extra == 'lightrag'
Requires-Dist: pipmaster>=0.4.0; extra == 'lightrag'
Provides-Extra: online
Requires-Dist: future>=1.0.0; extra == 'online'
Requires-Dist: graspologic; extra == 'online'
Requires-Dist: lancedb>=0.19.0; extra == 'online'
Requires-Dist: lightrag-hku>=1.2.2; extra == 'online'
Requires-Dist: nano-vectordb>=0.0.4.3; extra == 'online'
Requires-Dist: neo4j>=5.28.1; extra == 'online'
Requires-Dist: networkx>=3.4.2; extra == 'online'
Requires-Dist: pipmaster>=0.4.0; extra == 'online'
Requires-Dist: pymongo>=4.11.1; extra == 'online'
